Metadata-Version: 1.0
Name: faiss-centos
Version: 1.5.2
Summary: A library for efficient similarity search and clustering of dense vectors
Home-page: https://github.com/facebookresearch/faiss
Author: Matthijs Douze, Jeff Johnson, Herve Jegou, Lucas Hosseini
Author-email: matthijs@fb.com
License: MIT
Keywords: search nearest neighbors
Platform: UNKNOWN
